gdxtools/__init__.py
gdxtools/gdxrw.py
gdxtools-0.1.85.dist-info/LICENSE
gdxtools-0.1.85.dist-info/METADATA
gdxtools-0.1.85.dist-info/WHEEL
gdxtools-0.1.85.dist-info/top_level.txt
gdxtools-0.1.85.dist-info/RECORD
