Metadata-Version: 2.1
Name: gdxtools
Version: 0.1.85
Summary: A helper package to read and write GAMS GDX files
Home-page: https://github.com/boxblox/gdxtools
Author: Adam Christensen
Author-email: adam.christensen@gmail.com
License: UNKNOWN
Platform: UNKNOWN
Classifier: Programming Language :: Python :: 3
Classifier: License :: OSI Approved :: MIT License
Classifier: Operating System :: OS Independent
Requires-Python: >=3.6
Requires-Dist: gams
